[
    {
        "classId": 35,
        "staticData": {
            "INT": 25,
            "STR": 41,
            "CON": 32,
            "MEN": 26,
            "DEX": 34,
            "WIT": 12,
            "basePAtk": 4,
            "baseCritRate": 4,
            "baseAtkType": "FIST",
            "basePAtkSpd": 300,
            "basePDef": {
                "chest": 31,
                "legs": 18,
                "head": 12,
                "feet": 7,
                "gloves": 8,
                "underwear": 3,
                "cloak": 1
            },
            "baseMAtk": 6,
            "baseMDef": {
                "rear": 9,
                "lear": 9,
                "rfinger": 5,
                "lfinger": 5,
                "neck": 13
            },
            "baseCanPenetrate": 0,
            "baseAtkRange": 20,
            "baseDamRange": {
                "verticalDirection": 0,
                "horizontalDirection": 0,
                "distance": 26,
                "width": 120
            },
            "baseRndDam": 10,
            "baseMoveSpd": {
                "walk": 85,
                "run": 122,
                "slowSwim": 50,
                "fastSwim": 50
            },
            "baseBreath": 150,
            "baseSafeFall": 350,
            "collisionMale": {
                "radius": 7,
                "height": 23
            },
            "collisionFemale": {
                "radius": 7,
                "height": 23
            }
        },
        "creationPoints": [
            {
                "x": 28295,
                "y": 11063,
                "z": -4224
            },
            {
                "x": 28302,
                "y": 11008,
                "z": -4224
            },
            {
                "x": 28377,
                "y": 10916,
                "z": -4224
            },
            {
                "x": 28456,
                "y": 10997,
                "z": -4224
            },
            {
                "x": 28461,
                "y": 11044,
                "z": -4224
            },
            {
                "x": 28395,
                "y": 11127,
                "z": -4224
            }
        ],
        "lvlUpgainData": [
            {
                "level": 1,
                "hp": 94,
                "mp": 30,
                "cp": 47,
                "hpRegen": 2,
                "mpRegen": 0.9,
                "cpRegen": 2
            },
            {
                "level": 2,
                "hp": 107.65,
                "mp": 35.46,
                "cp": 53.825,
                "hpRegen": 2.05,
                "mpRegen": 0.9,
                "cpRegen": 2
            },
            {
                "level": 3,
                "hp": 121.45,
                "mp": 40.98,
                "cp": 60.725,
                "hpRegen": 2.1,
                "mpRegen": 0.9,
                "cpRegen": 2
            },
            {
                "level": 4,
                "hp": 135.4,
                "mp": 46.56,
                "cp": 67.7,
                "hpRegen": 2.15,
                "mpRegen": 0.9,
                "cpRegen": 2
            },
            {
                "level": 5,
                "hp": 149.5,
                "mp": 52.2,
                "cp": 74.75,
                "hpRegen": 2.2,
                "mpRegen": 0.9,
                "cpRegen": 2
            },
            {
                "level": 6,
                "hp": 163.75,
                "mp": 57.9,
                "cp": 81.875,
                "hpRegen": 2.25,
                "mpRegen": 0.9,
                "cpRegen": 2
            },
            {
                "level": 7,
                "hp": 178.15,
                "mp": 63.66,
                "cp": 89.075,
                "hpRegen": 2.3,
                "mpRegen": 0.9,
                "cpRegen": 2
            },
            {
                "level": 8,
                "hp": 192.7,
                "mp": 69.48,
                "cp": 96.35,
                "hpRegen": 2.35,
                "mpRegen": 0.9,
                "cpRegen": 2
            },
            {
                "level": 9,
                "hp": 207.4,
                "mp": 75.36,
                "cp": 103.7,
                "hpRegen": 2.4,
                "mpRegen": 0.9,
                "cpRegen": 2
            },
            {
                "level": 10,
                "hp": 222.25,
                "mp": 81.3,
                "cp": 111.125,
                "hpRegen": 2.45,
                "mpRegen": 0.9,
                "cpRegen": 2
            },
            {
                "level": 11,
                "hp": 237.25,
                "mp": 87.3,
                "cp": 118.625,
                "hpRegen": 2.5,
                "mpRegen": 1.2,
                "cpRegen": 2.5
            },
            {
                "level": 12,
                "hp": 252.4,
                "mp": 93.36,
                "cp": 126.2,
                "hpRegen": 2.6,
                "mpRegen": 1.2,
                "cpRegen": 2.5
            },
            {
                "level": 13,
                "hp": 267.7,
                "mp": 99.48,
                "cp": 133.85,
                "hpRegen": 2.7,
                "mpRegen": 1.2,
                "cpRegen": 2.5
            },
            {
                "level": 14,
                "hp": 283.15,
                "mp": 105.66,
                "cp": 141.575,
                "hpRegen": 2.8,
                "mpRegen": 1.2,
                "cpRegen": 2.5
            },
            {
                "level": 15,
                "hp": 298.75,
                "mp": 111.9,
                "cp": 149.375,
                "hpRegen": 2.9,
                "mpRegen": 1.2,
                "cpRegen": 2.5
            },
            {
                "level": 16,
                "hp": 314.5,
                "mp": 118.2,
                "cp": 157.25,
                "hpRegen": 3,
                "mpRegen": 1.2,
                "cpRegen": 2.5
            },
            {
                "level": 17,
                "hp": 330.4,
                "mp": 124.56,
                "cp": 165.2,
                "hpRegen": 3.1,
                "mpRegen": 1.2,
                "cpRegen": 2.5
            },
            {
                "level": 18,
                "hp": 346.45,
                "mp": 130.98,
                "cp": 173.225,
                "hpRegen": 3.2,
                "mpRegen": 1.2,
                "cpRegen": 2.5
            },
            {
                "level": 19,
                "hp": 362.65,
                "mp": 137.46,
                "cp": 181.325,
                "hpRegen": 3.3,
                "mpRegen": 1.2,
                "cpRegen": 2.5
            },
            {
                "level": 20,
                "hp": 379,
                "mp": 144,
                "cp": 189.5,
                "hpRegen": 3.4,
                "mpRegen": 1.2,
                "cpRegen": 2.5
            },
            {
                "level": 21,
                "hp": 412,
                "mp": 153.9,
                "cp": 206,
                "hpRegen": 3.5,
                "mpRegen": 1.5,
                "cpRegen": 3.5
            },
            {
                "level": 22,
                "hp": 445.3,
                "mp": 163.89,
                "cp": 222.65,
                "hpRegen": 3.6,
                "mpRegen": 1.5,
                "cpRegen": 3.5
            },
            {
                "level": 23,
                "hp": 478.9,
                "mp": 173.97,
                "cp": 239.45,
                "hpRegen": 3.7,
                "mpRegen": 1.5,
                "cpRegen": 3.5
            },
            {
                "level": 24,
                "hp": 512.8,
                "mp": 184.14,
                "cp": 256.4,
                "hpRegen": 3.8,
                "mpRegen": 1.5,
                "cpRegen": 3.5
            },
            {
                "level": 25,
                "hp": 547,
                "mp": 194.4,
                "cp": 273.5,
                "hpRegen": 3.9,
                "mpRegen": 1.5,
                "cpRegen": 3.5
            },
            {
                "level": 26,
                "hp": 581.5,
                "mp": 204.75,
                "cp": 290.75,
                "hpRegen": 4,
                "mpRegen": 1.5,
                "cpRegen": 3.5
            },
            {
                "level": 27,
                "hp": 616.3,
                "mp": 215.19,
                "cp": 308.15,
                "hpRegen": 4.1,
                "mpRegen": 1.5,
                "cpRegen": 3.5
            },
            {
                "level": 28,
                "hp": 651.4,
                "mp": 225.72,
                "cp": 325.7,
                "hpRegen": 4.2,
                "mpRegen": 1.5,
                "cpRegen": 3.5
            },
            {
                "level": 29,
                "hp": 686.8,
                "mp": 236.34,
                "cp": 343.4,
                "hpRegen": 4.3,
                "mpRegen": 1.5,
                "cpRegen": 3.5
            },
            {
                "level": 30,
                "hp": 722.5,
                "mp": 247.05,
                "cp": 361.25,
                "hpRegen": 4.4,
                "mpRegen": 1.5,
                "cpRegen": 3.5
            },
            {
                "level": 31,
                "hp": 758.5,
                "mp": 257.85,
                "cp": 379.25,
                "hpRegen": 4.5,
                "mpRegen": 1.8,
                "cpRegen": 4.5
            },
            {
                "level": 32,
                "hp": 794.8,
                "mp": 268.74,
                "cp": 397.4,
                "hpRegen": 4.6,
                "mpRegen": 1.8,
                "cpRegen": 4.5
            },
            {
                "level": 33,
                "hp": 831.4,
                "mp": 279.72,
                "cp": 415.7,
                "hpRegen": 4.7,
                "mpRegen": 1.8,
                "cpRegen": 4.5
            },
            {
                "level": 34,
                "hp": 868.3,
                "mp": 290.79,
                "cp": 434.15,
                "hpRegen": 4.8,
                "mpRegen": 1.8,
                "cpRegen": 4.5
            },
            {
                "level": 35,
                "hp": 905.5,
                "mp": 301.95,
                "cp": 452.75,
                "hpRegen": 4.9,
                "mpRegen": 1.8,
                "cpRegen": 4.5
            },
            {
                "level": 36,
                "hp": 943,
                "mp": 313.2,
                "cp": 471.5,
                "hpRegen": 5,
                "mpRegen": 1.8,
                "cpRegen": 4.5
            },
            {
                "level": 37,
                "hp": 980.8,
                "mp": 324.54,
                "cp": 490.4,
                "hpRegen": 5.1,
                "mpRegen": 1.8,
                "cpRegen": 4.5
            },
            {
                "level": 38,
                "hp": 1018.9,
                "mp": 335.97,
                "cp": 509.45,
                "hpRegen": 5.2,
                "mpRegen": 1.8,
                "cpRegen": 4.5
            },
            {
                "level": 39,
                "hp": 1057.3,
                "mp": 347.49,
                "cp": 528.65,
                "hpRegen": 5.3,
                "mpRegen": 1.8,
                "cpRegen": 4.5
            },
            {
                "level": 40,
                "hp": 1096,
                "mp": 359.1,
                "cp": 548,
                "hpRegen": 5.4,
                "mpRegen": 1.8,
                "cpRegen": 4.5
            },
            {
                "level": 41,
                "hp": 1135,
                "mp": 370.8,
                "cp": 567.5,
                "hpRegen": 5.5,
                "mpRegen": 2.1,
                "cpRegen": 5.5
            },
            {
                "level": 42,
                "hp": 1174.3,
                "mp": 382.59,
                "cp": 587.15,
                "hpRegen": 5.6,
                "mpRegen": 2.1,
                "cpRegen": 5.5
            },
            {
                "level": 43,
                "hp": 1213.9,
                "mp": 394.47,
                "cp": 606.95,
                "hpRegen": 5.7,
                "mpRegen": 2.1,
                "cpRegen": 5.5
            },
            {
                "level": 44,
                "hp": 1253.8,
                "mp": 406.44,
                "cp": 626.9,
                "hpRegen": 5.8,
                "mpRegen": 2.1,
                "cpRegen": 5.5
            },
            {
                "level": 45,
                "hp": 1294,
                "mp": 418.5,
                "cp": 647,
                "hpRegen": 5.9,
                "mpRegen": 2.1,
                "cpRegen": 5.5
            },
            {
                "level": 46,
                "hp": 1334.5,
                "mp": 430.65,
                "cp": 667.25,
                "hpRegen": 6,
                "mpRegen": 2.1,
                "cpRegen": 5.5
            },
            {
                "level": 47,
                "hp": 1375.3,
                "mp": 442.89,
                "cp": 687.65,
                "hpRegen": 6.1,
                "mpRegen": 2.1,
                "cpRegen": 5.5
            },
            {
                "level": 48,
                "hp": 1416.4,
                "mp": 455.22,
                "cp": 708.2,
                "hpRegen": 6.2,
                "mpRegen": 2.1,
                "cpRegen": 5.5
            },
            {
                "level": 49,
                "hp": 1457.8,
                "mp": 467.64,
                "cp": 728.9,
                "hpRegen": 6.3,
                "mpRegen": 2.1,
                "cpRegen": 5.5
            },
            {
                "level": 50,
                "hp": 1499.5,
                "mp": 480.15,
                "cp": 749.75,
                "hpRegen": 6.4,
                "mpRegen": 2.1,
                "cpRegen": 5.5
            },
            {
                "level": 51,
                "hp": 1541.5,
                "mp": 492.75,
                "cp": 770.75,
                "hpRegen": 6.5,
                "mpRegen": 2.4,
                "cpRegen": 6.5
            },
            {
                "level": 52,
                "hp": 1583.8,
                "mp": 505.44,
                "cp": 791.9,
                "hpRegen": 6.6,
                "mpRegen": 2.4,
                "cpRegen": 6.5
            },
            {
                "level": 53,
                "hp": 1626.4,
                "mp": 518.22,
                "cp": 813.2,
                "hpRegen": 6.7,
                "mpRegen": 2.4,
                "cpRegen": 6.5
            },
            {
                "level": 54,
                "hp": 1669.3,
                "mp": 531.09,
                "cp": 834.65,
                "hpRegen": 6.8,
                "mpRegen": 2.4,
                "cpRegen": 6.5
            },
            {
                "level": 55,
                "hp": 1712.5,
                "mp": 544.05,
                "cp": 856.25,
                "hpRegen": 6.9,
                "mpRegen": 2.4,
                "cpRegen": 6.5
            },
            {
                "level": 56,
                "hp": 1756,
                "mp": 557.1,
                "cp": 878,
                "hpRegen": 7,
                "mpRegen": 2.4,
                "cpRegen": 6.5
            },
            {
                "level": 57,
                "hp": 1799.8,
                "mp": 570.24,
                "cp": 899.9,
                "hpRegen": 7.1,
                "mpRegen": 2.4,
                "cpRegen": 6.5
            },
            {
                "level": 58,
                "hp": 1843.9,
                "mp": 583.47,
                "cp": 921.95,
                "hpRegen": 7.2,
                "mpRegen": 2.4,
                "cpRegen": 6.5
            },
            {
                "level": 59,
                "hp": 1888.3,
                "mp": 596.79,
                "cp": 944.15,
                "hpRegen": 7.3,
                "mpRegen": 2.4,
                "cpRegen": 6.5
            },
            {
                "level": 60,
                "hp": 1933,
                "mp": 610.2,
                "cp": 966.5,
                "hpRegen": 7.4,
                "mpRegen": 2.4,
                "cpRegen": 6.5
            },
            {
                "level": 61,
                "hp": 1978,
                "mp": 623.7,
                "cp": 989,
                "hpRegen": 7.5,
                "mpRegen": 2.7,
                "cpRegen": 7.5
            },
            {
                "level": 62,
                "hp": 2023.3,
                "mp": 637.29,
                "cp": 1011.65,
                "hpRegen": 7.6,
                "mpRegen": 2.7,
                "cpRegen": 7.5
            },
            {
                "level": 63,
                "hp": 2068.9,
                "mp": 650.97,
                "cp": 1034.45,
                "hpRegen": 7.7,
                "mpRegen": 2.7,
                "cpRegen": 7.5
            },
            {
                "level": 64,
                "hp": 2114.8,
                "mp": 664.74,
                "cp": 1057.4,
                "hpRegen": 7.8,
                "mpRegen": 2.7,
                "cpRegen": 7.5
            },
            {
                "level": 65,
                "hp": 2161,
                "mp": 678.6,
                "cp": 1080.5,
                "hpRegen": 7.9,
                "mpRegen": 2.7,
                "cpRegen": 7.5
            },
            {
                "level": 66,
                "hp": 2207.5,
                "mp": 692.55,
                "cp": 1103.75,
                "hpRegen": 8,
                "mpRegen": 2.7,
                "cpRegen": 7.5
            },
            {
                "level": 67,
                "hp": 2254.3,
                "mp": 706.59,
                "cp": 1127.15,
                "hpRegen": 8.1,
                "mpRegen": 2.7,
                "cpRegen": 7.5
            },
            {
                "level": 68,
                "hp": 2301.4,
                "mp": 720.72,
                "cp": 1150.7,
                "hpRegen": 8.2,
                "mpRegen": 2.7,
                "cpRegen": 7.5
            },
            {
                "level": 69,
                "hp": 2348.8,
                "mp": 734.94,
                "cp": 1174.4,
                "hpRegen": 8.3,
                "mpRegen": 2.7,
                "cpRegen": 7.5
            },
            {
                "level": 70,
                "hp": 2396.5,
                "mp": 749.25,
                "cp": 1198.25,
                "hpRegen": 8.4,
                "mpRegen": 2.7,
                "cpRegen": 7.5
            },
            {
                "level": 71,
                "hp": 2444.5,
                "mp": 763.65,
                "cp": 1222.25,
                "hpRegen": 8.5,
                "mpRegen": 3,
                "cpRegen": 8.5
            },
            {
                "level": 72,
                "hp": 2492.8,
                "mp": 778.14,
                "cp": 1246.4,
                "hpRegen": 8.6,
                "mpRegen": 3,
                "cpRegen": 8.5
            },
            {
                "level": 73,
                "hp": 2541.4,
                "mp": 792.72,
                "cp": 1270.7,
                "hpRegen": 8.7,
                "mpRegen": 3,
                "cpRegen": 8.5
            },
            {
                "level": 74,
                "hp": 2590.3,
                "mp": 807.39,
                "cp": 1295.15,
                "hpRegen": 8.8,
                "mpRegen": 3,
                "cpRegen": 8.5
            },
            {
                "level": 75,
                "hp": 2639.5,
                "mp": 822.15,
                "cp": 1319.75,
                "hpRegen": 8.9,
                "mpRegen": 3,
                "cpRegen": 8.5
            },
            {
                "level": 76,
                "hp": 2689,
                "mp": 837,
                "cp": 1344.5,
                "hpRegen": 9,
                "mpRegen": 3,
                "cpRegen": 8.5
            },
            {
                "level": 77,
                "hp": 2738.8,
                "mp": 851.94,
                "cp": 1369.4,
                "hpRegen": 9.1,
                "mpRegen": 3,
                "cpRegen": 8.5
            },
            {
                "level": 78,
                "hp": 2788.9,
                "mp": 866.97,
                "cp": 1394.45,
                "hpRegen": 9.2,
                "mpRegen": 3,
                "cpRegen": 8.5
            },
            {
                "level": 79,
                "hp": 2839.3,
                "mp": 882.09,
                "cp": 1419.65,
                "hpRegen": 9.3,
                "mpRegen": 3,
                "cpRegen": 8.5
            },
            {
                "level": 80,
                "hp": 2890,
                "mp": 897.3,
                "cp": 1445,
                "hpRegen": 9.4,
                "mpRegen": 3,
                "cpRegen": 8.5
            },
            {
                "level": 81,
                "hp": 2941,
                "mp": 912.6,
                "cp": 1470.5,
                "hpRegen": 9.5,
                "mpRegen": 3,
                "cpRegen": 8.5
            },
            {
                "level": 82,
                "hp": 2992.3,
                "mp": 927.99,
                "cp": 1496.15,
                "hpRegen": 9.6,
                "mpRegen": 3,
                "cpRegen": 8.5
            },
            {
                "level": 83,
                "hp": 3043.9,
                "mp": 943.47,
                "cp": 1521.95,
                "hpRegen": 9.7,
                "mpRegen": 3,
                "cpRegen": 8.5
            },
            {
                "level": 84,
                "hp": 3095.8,
                "mp": 959.04,
                "cp": 1547.9,
                "hpRegen": 9.8,
                "mpRegen": 3,
                "cpRegen": 8.5
            },
            {
                "level": 85,
                "hp": 3148,
                "mp": 974.7,
                "cp": 1574,
                "hpRegen": 9.9,
                "mpRegen": 3,
                "cpRegen": 8.5
            }
        ]
    }
]