{
    "config": {
        "trader": [],
        "showall": true,
        "notax": true,
        "keepenchanted": true,
        "bbsallowed": true,
        "disabled": false
    },
    "items": [
        {
            "production": [
                {
                    "id": 13728,
                    "count": 1,
                    "enchant": 0,
                    "fireAttr": 0,
                    "waterAttr": 0,
                    "earthAttr": 0,
                    "windAttr": 0,
                    "holyAttr": 0,
                    "unholyAttr": 0
                }
            ],
            "ingredient": [
                {
                    "id": 57,
                    "count": 300000,
                    "enchant": 0,
                    "mantainIngredient": true,
                    "fireAttr": 0,
                    "waterAttr": 0,
                    "earthAttr": 0,
                    "windAttr": 0,
                    "holyAttr": 0,
                    "unholyAttr": 0
                }
            ]
        },
        {
            "production": [
                {
                    "id": 13277,
                    "count": 1,
                    "enchant": 0,
                    "fireAttr": 0,
                    "waterAttr": 0,
                    "earthAttr": 0,
                    "windAttr": 0,
                    "holyAttr": 0,
                    "unholyAttr": 0
                }
            ],
            "ingredient": [
                {
                    "id": 57,
                    "count": 24000,
                    "enchant": 0,
                    "mantainIngredient": true,
                    "fireAttr": 0,
                    "waterAttr": 0,
                    "earthAttr": 0,
                    "windAttr": 0,
                    "holyAttr": 0,
                    "unholyAttr": 0
                }
            ]
        },
        {
            "production": [
                {
                    "id": 13726,
                    "count": 1,
                    "enchant": 0,
                    "fireAttr": 0,
                    "waterAttr": 0,
                    "earthAttr": 0,
                    "windAttr": 0,
                    "holyAttr": 0,
                    "unholyAttr": 0
                }
            ],
            "ingredient": [
                {
                    "id": 14009,
                    "count": 90,
                    "enchant": 0,
                    "mantainIngredient": true,
                    "fireAttr": 0,
                    "waterAttr": 0,
                    "earthAttr": 0,
                    "windAttr": 0,
                    "holyAttr": 0,
                    "unholyAttr": 0
                },
                {
                    "id": 57,
                    "count": 400000,
                    "enchant": 0,
                    "mantainIngredient": true,
                    "fireAttr": 0,
                    "waterAttr": 0,
                    "earthAttr": 0,
                    "windAttr": 0,
                    "holyAttr": 0,
                    "unholyAttr": 0
                }
            ]
        },
        {
            "production": [
                {
                    "id": 13727,
                    "count": 1,
                    "enchant": 0,
                    "fireAttr": 0,
                    "waterAttr": 0,
                    "earthAttr": 0,
                    "windAttr": 0,
                    "holyAttr": 0,
                    "unholyAttr": 0
                }
            ],
            "ingredient": [
                {
                    "id": 14009,
                    "count": 90,
                    "enchant": 0,
                    "mantainIngredient": true,
                    "fireAttr": 0,
                    "waterAttr": 0,
                    "earthAttr": 0,
                    "windAttr": 0,
                    "holyAttr": 0,
                    "unholyAttr": 0
                },
                {
                    "id": 57,
                    "count": 400000,
                    "enchant": 0,
                    "mantainIngredient": true,
                    "fireAttr": 0,
                    "waterAttr": 0,
                    "earthAttr": 0,
                    "windAttr": 0,
                    "holyAttr": 0,
                    "unholyAttr": 0
                }
            ]
        },
        {
            "production": [
                {
                    "id": 14028,
                    "count": 1,
                    "enchant": 0,
                    "fireAttr": 0,
                    "waterAttr": 0,
                    "earthAttr": 0,
                    "windAttr": 0,
                    "holyAttr": 0,
                    "unholyAttr": 0
                }
            ],
            "ingredient": [
                {
                    "id": 14011,
                    "count": 90,
                    "enchant": 0,
                    "mantainIngredient": true,
                    "fireAttr": 0,
                    "waterAttr": 0,
                    "earthAttr": 0,
                    "windAttr": 0,
                    "holyAttr": 0,
                    "unholyAttr": 0
                },
                {
                    "id": 57,
                    "count": 400000,
                    "enchant": 0,
                    "mantainIngredient": true,
                    "fireAttr": 0,
                    "waterAttr": 0,
                    "earthAttr": 0,
                    "windAttr": 0,
                    "holyAttr": 0,
                    "unholyAttr": 0
                }
            ]
        },
        {
            "production": [
                {
                    "id": 14029,
                    "count": 1,
                    "enchant": 0,
                    "fireAttr": 0,
                    "waterAttr": 0,
                    "earthAttr": 0,
                    "windAttr": 0,
                    "holyAttr": 0,
                    "unholyAttr": 0
                }
            ],
            "ingredient": [
                {
                    "id": 14010,
                    "count": 90,
                    "enchant": 0,
                    "mantainIngredient": true,
                    "fireAttr": 0,
                    "waterAttr": 0,
                    "earthAttr": 0,
                    "windAttr": 0,
                    "holyAttr": 0,
                    "unholyAttr": 0
                },
                {
                    "id": 57,
                    "count": 400000,
                    "enchant": 0,
                    "mantainIngredient": true,
                    "fireAttr": 0,
                    "waterAttr": 0,
                    "earthAttr": 0,
                    "windAttr": 0,
                    "holyAttr": 0,
                    "unholyAttr": 0
                }
            ]
        },
        {
            "production": [
                {
                    "id": 14030,
                    "count": 1,
                    "enchant": 0,
                    "fireAttr": 0,
                    "waterAttr": 0,
                    "earthAttr": 0,
                    "windAttr": 0,
                    "holyAttr": 0,
                    "unholyAttr": 0
                }
            ],
            "ingredient": [
                {
                    "id": 14010,
                    "count": 90,
                    "enchant": 0,
                    "mantainIngredient": true,
                    "fireAttr": 0,
                    "waterAttr": 0,
                    "earthAttr": 0,
                    "windAttr": 0,
                    "holyAttr": 0,
                    "unholyAttr": 0
                },
                {
                    "id": 57,
                    "count": 400000,
                    "enchant": 0,
                    "mantainIngredient": true,
                    "fireAttr": 0,
                    "waterAttr": 0,
                    "earthAttr": 0,
                    "windAttr": 0,
                    "holyAttr": 0,
                    "unholyAttr": 0
                }
            ]
        },
        {
            "production": [
                {
                    "id": 14031,
                    "count": 1,
                    "enchant": 0,
                    "fireAttr": 0,
                    "waterAttr": 0,
                    "earthAttr": 0,
                    "windAttr": 0,
                    "holyAttr": 0,
                    "unholyAttr": 0
                }
            ],
            "ingredient": [
                {
                    "id": 14010,
                    "count": 90,
                    "enchant": 0,
                    "mantainIngredient": true,
                    "fireAttr": 0,
                    "waterAttr": 0,
                    "earthAttr": 0,
                    "windAttr": 0,
                    "holyAttr": 0,
                    "unholyAttr": 0
                },
                {
                    "id": 57,
                    "count": 400000,
                    "enchant": 0,
                    "mantainIngredient": true,
                    "fireAttr": 0,
                    "waterAttr": 0,
                    "earthAttr": 0,
                    "windAttr": 0,
                    "holyAttr": 0,
                    "unholyAttr": 0
                }
            ]
        },
        {
            "production": [
                {
                    "id": 14032,
                    "count": 1,
                    "enchant": 0,
                    "fireAttr": 0,
                    "waterAttr": 0,
                    "earthAttr": 0,
                    "windAttr": 0,
                    "holyAttr": 0,
                    "unholyAttr": 0
                }
            ],
            "ingredient": [
                {
                    "id": 14010,
                    "count": 90,
                    "enchant": 0,
                    "mantainIngredient": true,
                    "fireAttr": 0,
                    "waterAttr": 0,
                    "earthAttr": 0,
                    "windAttr": 0,
                    "holyAttr": 0,
                    "unholyAttr": 0
                },
                {
                    "id": 57,
                    "count": 400000,
                    "enchant": 0,
                    "mantainIngredient": true,
                    "fireAttr": 0,
                    "waterAttr": 0,
                    "earthAttr": 0,
                    "windAttr": 0,
                    "holyAttr": 0,
                    "unholyAttr": 0
                }
            ]
        },
        {
            "production": [
                {
                    "id": 14033,
                    "count": 1,
                    "enchant": 0,
                    "fireAttr": 0,
                    "waterAttr": 0,
                    "earthAttr": 0,
                    "windAttr": 0,
                    "holyAttr": 0,
                    "unholyAttr": 0
                }
            ],
            "ingredient": [
                {
                    "id": 14010,
                    "count": 90,
                    "enchant": 0,
                    "mantainIngredient": true,
                    "fireAttr": 0,
                    "waterAttr": 0,
                    "earthAttr": 0,
                    "windAttr": 0,
                    "holyAttr": 0,
                    "unholyAttr": 0
                },
                {
                    "id": 57,
                    "count": 400000,
                    "enchant": 0,
                    "mantainIngredient": true,
                    "fireAttr": 0,
                    "waterAttr": 0,
                    "earthAttr": 0,
                    "windAttr": 0,
                    "holyAttr": 0,
                    "unholyAttr": 0
                }
            ]
        },
        {
            "production": [
                {
                    "id": 14034,
                    "count": 1,
                    "enchant": 0,
                    "fireAttr": 0,
                    "waterAttr": 0,
                    "earthAttr": 0,
                    "windAttr": 0,
                    "holyAttr": 0,
                    "unholyAttr": 0
                }
            ],
            "ingredient": [
                {
                    "id": 14011,
                    "count": 90,
                    "enchant": 0,
                    "mantainIngredient": true,
                    "fireAttr": 0,
                    "waterAttr": 0,
                    "earthAttr": 0,
                    "windAttr": 0,
                    "holyAttr": 0,
                    "unholyAttr": 0
                },
                {
                    "id": 57,
                    "count": 400000,
                    "enchant": 0,
                    "mantainIngredient": true,
                    "fireAttr": 0,
                    "waterAttr": 0,
                    "earthAttr": 0,
                    "windAttr": 0,
                    "holyAttr": 0,
                    "unholyAttr": 0
                }
            ]
        },
        {
            "production": [
                {
                    "id": 14035,
                    "count": 1,
                    "enchant": 0,
                    "fireAttr": 0,
                    "waterAttr": 0,
                    "earthAttr": 0,
                    "windAttr": 0,
                    "holyAttr": 0,
                    "unholyAttr": 0
                }
            ],
            "ingredient": [
                {
                    "id": 14011,
                    "count": 90,
                    "enchant": 0,
                    "mantainIngredient": true,
                    "fireAttr": 0,
                    "waterAttr": 0,
                    "earthAttr": 0,
                    "windAttr": 0,
                    "holyAttr": 0,
                    "unholyAttr": 0
                },
                {
                    "id": 57,
                    "count": 400000,
                    "enchant": 0,
                    "mantainIngredient": true,
                    "fireAttr": 0,
                    "waterAttr": 0,
                    "earthAttr": 0,
                    "windAttr": 0,
                    "holyAttr": 0,
                    "unholyAttr": 0
                }
            ]
        },
        {
            "production": [
                {
                    "id": 14036,
                    "count": 1,
                    "enchant": 0,
                    "fireAttr": 0,
                    "waterAttr": 0,
                    "earthAttr": 0,
                    "windAttr": 0,
                    "holyAttr": 0,
                    "unholyAttr": 0
                }
            ],
            "ingredient": [
                {
                    "id": 14011,
                    "count": 90,
                    "enchant": 0,
                    "mantainIngredient": true,
                    "fireAttr": 0,
                    "waterAttr": 0,
                    "earthAttr": 0,
                    "windAttr": 0,
                    "holyAttr": 0,
                    "unholyAttr": 0
                },
                {
                    "id": 57,
                    "count": 400000,
                    "enchant": 0,
                    "mantainIngredient": true,
                    "fireAttr": 0,
                    "waterAttr": 0,
                    "earthAttr": 0,
                    "windAttr": 0,
                    "holyAttr": 0,
                    "unholyAttr": 0
                }
            ]
        },
        {
            "production": [
                {
                    "id": 14037,
                    "count": 1,
                    "enchant": 0,
                    "fireAttr": 0,
                    "waterAttr": 0,
                    "earthAttr": 0,
                    "windAttr": 0,
                    "holyAttr": 0,
                    "unholyAttr": 0
                }
            ],
            "ingredient": [
                {
                    "id": 14009,
                    "count": 90,
                    "enchant": 0,
                    "mantainIngredient": true,
                    "fireAttr": 0,
                    "waterAttr": 0,
                    "earthAttr": 0,
                    "windAttr": 0,
                    "holyAttr": 0,
                    "unholyAttr": 0
                },
                {
                    "id": 57,
                    "count": 400000,
                    "enchant": 0,
                    "mantainIngredient": true,
                    "fireAttr": 0,
                    "waterAttr": 0,
                    "earthAttr": 0,
                    "windAttr": 0,
                    "holyAttr": 0,
                    "unholyAttr": 0
                }
            ]
        },
        {
            "production": [
                {
                    "id": 14104,
                    "count": 1,
                    "enchant": 0,
                    "fireAttr": 0,
                    "waterAttr": 0,
                    "earthAttr": 0,
                    "windAttr": 0,
                    "holyAttr": 0,
                    "unholyAttr": 0
                }
            ],
            "ingredient": [
                {
                    "id": 14009,
                    "count": 50,
                    "enchant": 0,
                    "mantainIngredient": true,
                    "fireAttr": 0,
                    "waterAttr": 0,
                    "earthAttr": 0,
                    "windAttr": 0,
                    "holyAttr": 0,
                    "unholyAttr": 0
                },
                {
                    "id": 57,
                    "count": 80000,
                    "enchant": 0,
                    "mantainIngredient": true,
                    "fireAttr": 0,
                    "waterAttr": 0,
                    "earthAttr": 0,
                    "windAttr": 0,
                    "holyAttr": 0,
                    "unholyAttr": 0
                }
            ]
        },
        {
            "production": [
                {
                    "id": 13993,
                    "count": 1,
                    "enchant": 0,
                    "fireAttr": 0,
                    "waterAttr": 0,
                    "earthAttr": 0,
                    "windAttr": 0,
                    "holyAttr": 0,
                    "unholyAttr": 0
                }
            ],
            "ingredient": [
                {
                    "id": 14009,
                    "count": 200,
                    "enchant": 0,
                    "mantainIngredient": true,
                    "fireAttr": 0,
                    "waterAttr": 0,
                    "earthAttr": 0,
                    "windAttr": 0,
                    "holyAttr": 0,
                    "unholyAttr": 0
                },
                {
                    "id": 57,
                    "count": 600000,
                    "enchant": 0,
                    "mantainIngredient": true,
                    "fireAttr": 0,
                    "waterAttr": 0,
                    "earthAttr": 0,
                    "windAttr": 0,
                    "holyAttr": 0,
                    "unholyAttr": 0
                }
            ]
        },
        {
            "production": [
                {
                    "id": 13994,
                    "count": 1,
                    "enchant": 0,
                    "fireAttr": 0,
                    "waterAttr": 0,
                    "earthAttr": 0,
                    "windAttr": 0,
                    "holyAttr": 0,
                    "unholyAttr": 0
                }
            ],
            "ingredient": [
                {
                    "id": 14009,
                    "count": 200,
                    "enchant": 0,
                    "mantainIngredient": true,
                    "fireAttr": 0,
                    "waterAttr": 0,
                    "earthAttr": 0,
                    "windAttr": 0,
                    "holyAttr": 0,
                    "unholyAttr": 0
                },
                {
                    "id": 57,
                    "count": 600000,
                    "enchant": 0,
                    "mantainIngredient": true,
                    "fireAttr": 0,
                    "waterAttr": 0,
                    "earthAttr": 0,
                    "windAttr": 0,
                    "holyAttr": 0,
                    "unholyAttr": 0
                }
            ]
        },
        {
            "production": [
                {
                    "id": 13995,
                    "count": 1,
                    "enchant": 0,
                    "fireAttr": 0,
                    "waterAttr": 0,
                    "earthAttr": 0,
                    "windAttr": 0,
                    "holyAttr": 0,
                    "unholyAttr": 0
                }
            ],
            "ingredient": [
                {
                    "id": 14009,
                    "count": 200,
                    "enchant": 0,
                    "mantainIngredient": true,
                    "fireAttr": 0,
                    "waterAttr": 0,
                    "earthAttr": 0,
                    "windAttr": 0,
                    "holyAttr": 0,
                    "unholyAttr": 0
                },
                {
                    "id": 57,
                    "count": 600000,
                    "enchant": 0,
                    "mantainIngredient": true,
                    "fireAttr": 0,
                    "waterAttr": 0,
                    "earthAttr": 0,
                    "windAttr": 0,
                    "holyAttr": 0,
                    "unholyAttr": 0
                }
            ]
        },
        {
            "production": [
                {
                    "id": 13996,
                    "count": 1,
                    "enchant": 0,
                    "fireAttr": 0,
                    "waterAttr": 0,
                    "earthAttr": 0,
                    "windAttr": 0,
                    "holyAttr": 0,
                    "unholyAttr": 0
                }
            ],
            "ingredient": [
                {
                    "id": 14009,
                    "count": 200,
                    "enchant": 0,
                    "mantainIngredient": true,
                    "fireAttr": 0,
                    "waterAttr": 0,
                    "earthAttr": 0,
                    "windAttr": 0,
                    "holyAttr": 0,
                    "unholyAttr": 0
                },
                {
                    "id": 57,
                    "count": 600000,
                    "enchant": 0,
                    "mantainIngredient": true,
                    "fireAttr": 0,
                    "waterAttr": 0,
                    "earthAttr": 0,
                    "windAttr": 0,
                    "holyAttr": 0,
                    "unholyAttr": 0
                }
            ]
        },
        {
            "production": [
                {
                    "id": 13997,
                    "count": 1,
                    "enchant": 0,
                    "fireAttr": 0,
                    "waterAttr": 0,
                    "earthAttr": 0,
                    "windAttr": 0,
                    "holyAttr": 0,
                    "unholyAttr": 0
                }
            ],
            "ingredient": [
                {
                    "id": 14009,
                    "count": 200,
                    "enchant": 0,
                    "mantainIngredient": true,
                    "fireAttr": 0,
                    "waterAttr": 0,
                    "earthAttr": 0,
                    "windAttr": 0,
                    "holyAttr": 0,
                    "unholyAttr": 0
                },
                {
                    "id": 57,
                    "count": 600000,
                    "enchant": 0,
                    "mantainIngredient": true,
                    "fireAttr": 0,
                    "waterAttr": 0,
                    "earthAttr": 0,
                    "windAttr": 0,
                    "holyAttr": 0,
                    "unholyAttr": 0
                }
            ]
        },
        {
            "production": [
                {
                    "id": 13998,
                    "count": 1,
                    "enchant": 0,
                    "fireAttr": 0,
                    "waterAttr": 0,
                    "earthAttr": 0,
                    "windAttr": 0,
                    "holyAttr": 0,
                    "unholyAttr": 0
                }
            ],
            "ingredient": [
                {
                    "id": 14009,
                    "count": 200,
                    "enchant": 0,
                    "mantainIngredient": true,
                    "fireAttr": 0,
                    "waterAttr": 0,
                    "earthAttr": 0,
                    "windAttr": 0,
                    "holyAttr": 0,
                    "unholyAttr": 0
                },
                {
                    "id": 57,
                    "count": 600000,
                    "enchant": 0,
                    "mantainIngredient": true,
                    "fireAttr": 0,
                    "waterAttr": 0,
                    "earthAttr": 0,
                    "windAttr": 0,
                    "holyAttr": 0,
                    "unholyAttr": 0
                }
            ]
        },
        {
            "production": [
                {
                    "id": 13552,
                    "count": 1,
                    "enchant": 0,
                    "fireAttr": 0,
                    "waterAttr": 0,
                    "earthAttr": 0,
                    "windAttr": 0,
                    "holyAttr": 0,
                    "unholyAttr": 0
                }
            ],
            "ingredient": [
                {
                    "id": 57,
                    "count": 2600000,
                    "enchant": 0,
                    "mantainIngredient": true,
                    "fireAttr": 0,
                    "waterAttr": 0,
                    "earthAttr": 0,
                    "windAttr": 0,
                    "holyAttr": 0,
                    "unholyAttr": 0
                }
            ]
        },
        {
            "production": [
                {
                    "id": 13553,
                    "count": 1,
                    "enchant": 0,
                    "fireAttr": 0,
                    "waterAttr": 0,
                    "earthAttr": 0,
                    "windAttr": 0,
                    "holyAttr": 0,
                    "unholyAttr": 0
                }
            ],
            "ingredient": [
                {
                    "id": 57,
                    "count": 2600000,
                    "enchant": 0,
                    "mantainIngredient": true,
                    "fireAttr": 0,
                    "waterAttr": 0,
                    "earthAttr": 0,
                    "windAttr": 0,
                    "holyAttr": 0,
                    "unholyAttr": 0
                }
            ]
        },
        {
            "production": [
                {
                    "id": 13554,
                    "count": 1,
                    "enchant": 0,
                    "fireAttr": 0,
                    "waterAttr": 0,
                    "earthAttr": 0,
                    "windAttr": 0,
                    "holyAttr": 0,
                    "unholyAttr": 0
                }
            ],
            "ingredient": [
                {
                    "id": 57,
                    "count": 2600000,
                    "enchant": 0,
                    "mantainIngredient": true,
                    "fireAttr": 0,
                    "waterAttr": 0,
                    "earthAttr": 0,
                    "windAttr": 0,
                    "holyAttr": 0,
                    "unholyAttr": 0
                }
            ]
        }
    ]
}